django_jabber/__init__.py
django_jabber/conf.py
django_jabber-1.0.1.dist-info/DESCRIPTION.rst
django_jabber-1.0.1.dist-info/METADATA
django_jabber-1.0.1.dist-info/RECORD
django_jabber-1.0.1.dist-info/WHEEL
django_jabber-1.0.1.dist-info/metadata.json
django_jabber-1.0.1.dist-info/top_level.txt
