Metadata-Version: 2.0
Name: django-jabber
Version: 1.0.1
Summary: Send Jabber notifications from Django
Home-page: https://github.com/alexmorozov/django-jabber
Author: Alex Morozov
Author-email: inductor2000@mail.ru
License: UNKNOWN
Platform: UNKNOWN
Classifier: Development Status :: 2 - Pre-Alpha
Classifier: Programming Language :: Python
Classifier: Programming Language :: Python :: 2
Classifier: Programming Language :: Python :: 2.7
Classifier: Programming Language :: Python :: 3
Classifier: Programming Language :: Python :: 3.3
Requires-Dist: celery (>3)
Requires-Dist: django (>1.6)
Requires-Dist: sleekxmpp (==1.1.11)
